data_minion/__init__.py
data_minion/__main__.py
data_minion/add_average_grade.py
data_minion/app.py
data_minion/collect_class_lists.py
data_minion/collect_data.py
data_minion/files_and_folders.py
data_minion/handle_settings.py
data_minion/json_to_xlsx.py
data_minion/resources/__init__.py
data_minion/resources/minion.ico
data_minion/resources/minion.png
data_minion/resources/settings.json
data_minion/set_settings.py
data_minion/split_students.py
data_minion-0.1.0.dist-info/LICENSE
data_minion-0.1.0.dist-info/WHEEL
data_minion-0.1.0.dist-info/METADATA
data_minion-0.1.0.dist-info/RECORD
